[
    {
        "title": "Spotify API",
        "img": "spotify.png",
        "description": "An API like Spotify",
        "link": "https://github.com/pgm-jandeschacht/Spotify_API"
    },
    {
        "title": "Movie Application",
        "img": "movie.png",
        "description": "An app created in React",
        "link": "https://github.com/pgm-jandeschacht/Movie_Application"
    },
    {
        "title": "Developer Quiz",
        "img": "logo.png",
        "description": "A quiz for developers",
        "link": "https://github.com/pgm-jandeschacht/Developer_Quiz"
    },
    {
        "title": "Hike App",
        "img": "hike.png",
        "description": "A product site for a Walk-A-Wish",
        "link": "https://github.com/pgm-jandeschacht/Hike_App"
    },
    {
        "title": "Tinder Clone",
        "img": "test.png",
        "description": "A clone of Tinder",
        "link": "https://github.com/pgm-jandeschacht/Tinder_Clone"
    },
    {
        "title": "Webshop",
        "img": "shop.png",
        "description": "A webshop with database",
        "link": "https://github.com/pgm-jandeschacht/Webshop"
    },
    {
        "title": "Gentse Feesten",
        "img": "gent.svg",
        "description": "A clone site of Gentse Feesten",
        "link": "https://github.com/pgm-jandeschacht/Gentse_Feesten"
    },
    {
        "title": "Arne Quinze",
        "img": "logo.png",
        "description": "A clone site of Arne Quinze",
        "link": "https://github.com/pgm-jandeschacht/Arne_Quinze"
    }
]